pyuubin/__init__.py
pyuubin/__main__.py
pyuubin/__version__.py
pyuubin/api/__init__.py
pyuubin/api/__main__.py
pyuubin/api/app.py
pyuubin/api/v1.py
pyuubin/auth.py
pyuubin/connectors/__init__.py
pyuubin/connectors/smtp.py
pyuubin/connectors/stdout.py
pyuubin/db.py
pyuubin/exceptions.py
pyuubin/health.py
pyuubin/mailer.py
pyuubin/models.py
pyuubin/settings.py
pyuubin/templates.py
pyuubin/version.txt
pyuubin/worker.py
pyuubin-0.1.1.dist-info/LICENSE
pyuubin-0.1.1.dist-info/WHEEL
pyuubin-0.1.1.dist-info/METADATA
pyuubin-0.1.1.dist-info/RECORD
